eac_logchecker.py
eac_logchecker-0.8.1.dist-info/LICENSE
eac_logchecker-0.8.1.dist-info/METADATA
eac_logchecker-0.8.1.dist-info/WHEEL
eac_logchecker-0.8.1.dist-info/entry_points.txt
eac_logchecker-0.8.1.dist-info/top_level.txt
eac_logchecker-0.8.1.dist-info/RECORD
