Metadata-Version: 2.1
Name: eac-logchecker
Version: 0.8.1
Summary: Logchecker for logs generated by EAC
Home-page: https://github.com/OPSnet/eac_logchecker.py
Author: OPS
Author-email: noreply@mail.orpheus.network
License: MIT
Platform: UNKNOWN
Classifier: Development Status :: 5 - Production/Stable
Classifier: License :: OSI Approved :: MIT License
Classifier: Programming Language :: Python
Classifier: Programming Language :: Python :: 3
Classifier: Programming Language :: Python :: 3.5
Classifier: Programming Language :: Python :: 3.6
Classifier: Programming Language :: Python :: 3.7
Classifier: Programming Language :: Python :: 3.8
Requires-Python: >=3.5.0
Requires-Dist: pprp (==0.2.6)
